<?xml version='1.0' encoding="UTF-8"?>
<?xml-stylesheet href="..\.style\data.xsl" type="text/xsl"?>
  <instance source="file:/D:/workspaces/ofwi/RoadRunnerOriginal/output/vnwork/html/VNW_ophandauthau493146jd.html" name="VNW_ophandauthau493146jd">
    <and>
      <attribute label="_A_">Phụ Trách Bộ Phận Đấu Thầu job - VietnamWorks</attribute>
      <attribute label="_B_">Phụ Trách Bộ Phận Đấu Thầu</attribute>
      <attribute label="_C_">Phụ Trách Bộ Phận Đấu Thầu</attribute>
      <attribute label="_D_">Công Ty Cổ Phần KT-TM-DV Kỹ Nghệ Việt</attribute>
      <attribute label="_E_">158 Hoàng Hoa Thám, P.12, Q. Tân Bình, Tp.HCM</attribute>
      <attribute label="_F_">- Tổ chức, quản lý phòng đấu thầu theo qui định; - Chuẩn bị &amp; lập hồ sơ dự thầu (đơn nộp thầu, hồ sơ năng lực/kinh nghiệm &amp; hồ sơ kỹ thuật,..,); - Tham gia thực hiện &amp; kiểm tra việc bóc tách khối lượng bản vẽ theo hồ sơ yêu cầu; - Trao đổi các thông tin về dự án với khách hàng để lấy giá, phục vụ hoàn thành Hồ Sơ Đấu Thầu tối ưu nhất; - Kiểm tra tính đầy đủ, hợp lý, hợp lệ của khối lượng &amp; tiêu chuẩn vật tư thiết bị (lựa chọn vật tư thiết bị theo đúng tiêu chuẩn hồ sơ mời thầu); - Lập &amp; tập hợp bảng dự toán chi tiết theo Hồ sơ mời thầu; - Lập &amp; trình Ban Giám đốc xem xét và duyệt Hồ Sơ Đấu Thầu, kể cả bảng dự toán dự thầu; - Nghiên cứu và đề xuất BGĐ biện pháp chọn lựa tối ưu của Hồ Sơ Đấu Thầu; - Trực tiếp cùng Ban Giám đốc giải trình Hồ Sơ Đấu Thầu với khách hàng; - Theo dõi, thống kê &amp; báo cáo tình hình đấu thầu; - Trực tiếp tư vấn các giải pháp đến Ban Giám đốc về công tác đấu thầu; - Thực hiện công tác khác từ Ban Giám đốc.   Quyền lợi:  - Thu nhập cao, cạnh tranh; - Được hưởng đầy đủ các chế độ của người lao động do nhà nước CHXHCN Việt Nam quy định (BHXH, BHYT,BHTN...); - Thưởng các ngày lễ, tết, sinh nhật,… - Tháng lương thứ 13; thưởng dự án; thưởng đột xuất; - Và các chế độ phúc lợi khác như: Chăm sóc sức khỏe, thăm hỏi ốm đau, hiếu hỷ… - Được xem xét điều chỉnh lương 01 lần/ năm căn cứ vào năng lực công tác thực tế và kết quả cống hiến với công ty; - Môi trường làm việc thân thiện.</attribute>
      <attribute label="_G_">- Tốt nghiệp chuyên ngành kỹ thuật: Điện; - Chuyên môn thành thạo. Am hiểu các hệ thống liên quan là một lợi thế; - Tối thiểu 7 năm kinh nghiệm trong lĩnh vực chuyên ngành. Tối thiểu 3 năm ở vị trí tương đương; - Hiểu biết các tiêu chuẩn Việt Nam &amp; quốc tế về thiết kế, lắp đặt cơ điện các công trình dân dụng &amp; công nghiệp; - Có khả năng kiểm soát việc bóc tách khối lượng chính xác cho mỗi công trình. - Khả năng tập hợp và xử lý dữ liệu chính xác; - Có mối quan hệ, giao tiếp tốt với nhà cung cấp; - Khả năng làm việc nhóm tốt, tinh thần trách nhiệm cao; - Tiếng Anh giao tiếp tốt.</attribute>
      <attribute label="_H_">Manager</attribute>
      <attribute label="_I_">Electrical/ElectronicsPlanning/ProjectsExecutive management</attribute>
      <attribute label="_J_">Ho Chi Minh</attribute>
      <attribute label="_K_">Vietnamese</attribute>
      <attribute label="_L_">1201 Views</attribute>
      <attribute label="_M_">17 Aug Expires</attribute>
      <subtree>
<DIV class="row"> 
        <DIV class="col-md-3 col-sm-3 box-md "> 
         <DIV class="logo-cus"> 
          <IMG alt="Employer's logo - Công Ty Cổ Phần KT-TM-DV Kỹ Nghệ Việt" src="http://images.vietnamworks.com/pictureofcompany/83/4463882.gif"/> 
         </DIV> 
        </DIV> 
        <DIV class="col-md-9 col-sm-9"> 
         <H3> Công Ty Cổ Phần KT-TM-DV Kỹ Nghệ Việt <SMALL>158 Hoàng Hoa Thám, P.12, Q. Tân Bình, Tp.HCM</SMALL> </H3> 
        </DIV> 
        <DIV class="col-md-9 col-sm-9">  Contact person: 
         <STRONG>Ms.Hằng</STRONG> Company size: 
         <STRONG>100-499</STRONG>  
        </DIV> 
       </DIV>      </subtree>
      <attribute label="_N_">VIET CORP – Công Ty CP Kỹ Nghệ Việt - được chính thức thành lập vào năm 2004 là thành quả của hơn 10 năm hoạt động của những người sáng lập nhằm xây dựng hình ảnh Công Ty theo đúng như tên gọi của nó – một Công Ty với kỹ thuật cao tự hào được vận hành hoàn toàn bởi người Việt nam.   Danh sách các dự án do VIET CORP thực hiện thành công trong những năm vừa qua trong lĩnh vực Cơ Điện Lạnh (M&amp;E) cho các công trình dân dụng và công nghiệp của các Công Ty lớn đa quốc gia cũng như trong nước chính là những minh chứng cho chất lượng sản phẩm và dịch vụ của chúng tôi. View more  More jobs from this employer</attribute>
    </and>
  </instance>
