<?xml version='1.0' encoding="UTF-8"?>
<?xml-stylesheet href="..\.style\data.xsl" type="text/xsl"?>
  <instance source="file:/D:/workspaces/ofwi/RoadRunnerOriginal/output/vnwork/html/VNW_tcoordinator493245jd.html" name="VNW_tcoordinator493245jd">
    <and>
      <attribute label="_A_">An Architect To Work As Project Coordinator job - VietnamWorks</attribute>
      <attribute label="_B_">An Architect To Work As Project Coordinator</attribute>
      <attribute label="_C_">An Architect To Work As Project Coordinator</attribute>
      <attribute label="_D_">Nikken Sekkei Ltd</attribute>
      <attribute label="_E_">Suite 505, Block B, Indochina Park Tower, 04 Nguyen Dinh Chieu St., Dist. 1, HCMC</attribute>
      <attribute label="_F_">Nikken Sekkei Ltd is the lead architect providing a full design services package to a Vietnam’s leading commercial bank’s Headquarters in the heart of Hochiminh City. The project will soon be started in August 2014 and is anticipated to take several years. Nikken Sekkei Ltd shall work with the Client, the Client’s Project Manager (an American PM), and Nikken’s key local consultants including ARUP, PTW, etc. As the only Project Coordinator for this prominent project, you are responsible to: 1. Coordinate with the Client / Project Manager / Sub-consultants / Local authorities; 2. Attend periodical meetings with Client / Project Manager / Sub-consultants / Local authorities and prepare minutes of meeting; 3. Interpret in meetings with Client when and as required; 4. Translate documents (Vietnamese-English-Vietnamese) including official letters, referential documents, emails, etc. 5. Prepare official correspondences to related parties (usually to Client and authorities); 6. Handle submission documents to Client / Project Manager / Local authorities; 7. Handle applications to authorities for administrative permits (work permit, etc.) – with assistance of Nikken Sekkei’s Representative Office; 8. Conduct simple book-keeping of monthly expenses of the Project Office; 9. Coordinate with Nikken Sekkei’s Osaka and Tokyo offices in hotel and ticket reservation, and any other administration task required; 10. Assist the Project Manager and other Design Team Members in other tasks required for the project.</attribute>
      <attribute label="_G_">1. Job requirements: • A competent architect • At least 03 years experience in large-scale international projects. • Able to work under high pressure independently and also as part of a team. • Having a good overview of project, being able to manage tight deadlines. • Good communication skills, highly self-motivated, independent.   * Only qualified candidates should apply. * CV must be in English.  2. Job offers: • Monthly net salary: USD 900 – USD 1,000 •Transportation provided for business purposes, • Phone allowance provided, • 13th month salary, • Yearly salary review, • Annual leaves, • Work at: HCMC Office • Basic working time: Mon - Fri, 08:00am - 12:00am, 01:00pm - 05:00pm • Starting time: 4th week of August, 2014.  Application deadline: 22 August 2014 (but can be closed earlier as soon as the hiring process is successful)</attribute>
      <attribute label="_H_">Experienced (Non-Manager)</attribute>
      <attribute label="_I_">Architecture/Interior DesignCivil/ConstructionPlanning/Projects</attribute>
      <attribute label="_J_">Ho Chi Minh</attribute>
      <attribute label="_K_">English</attribute>
      <attribute label="_L_">1963 Views</attribute>
      <attribute label="_M_">17 Aug Expires</attribute>
      <subtree>
<DIV class="row"> 
        <DIV class="col-md-3 col-sm-3 box-md "> 
         <DIV class="logo-cus"> 
          <IMG alt="Employer's logo - Nikken Sekkei Ltd" src="http://images.vietnamworks.com/pictureofcompany/66/4039020.gif"/> 
         </DIV> 
        </DIV> 
        <DIV class="col-md-9 col-sm-9"> 
         <H3> Nikken Sekkei Ltd <SMALL>Suite 505, Block B, Indochina Park Tower, 04 Nguyen Dinh Chieu St., Dist. 1, HCMC</SMALL> </H3> 
        </DIV> 
        <DIV class="col-md-9 col-sm-9">  Contact person: 
         <STRONG>Mr. Nguyễn Như Thụy</STRONG> Company size: 
         <STRONG>1,000-4,999</STRONG>  
        </DIV> 
       </DIV>      </subtree>
      <attribute label="_N_">Website: http://www.nikken.jp/en/  Nikken Sekkei Ltd is a Japan-based comprehensive and multi-disciplinary consulting firm providing worldwide services in all related fields, including city and urban planning, site planning and civil engineering, architectural and interior design, structural engineering, mechanical &amp; electrical engineering, landscape design, as well as construction project management and supervision services during construction.  Established in 1900, Nikken Sekkei Ltd has completed over 20,000 projects in over 40 countries, actively contributing to the social welfare and economy in Japan and on a global scale.  Among the most prestigious projects of Nikken Sekkei Ltd in Vietnam are the National Museum of History, VNTA Headquarters, the Master Planning at scale 1/2000 of the existing expanded area of HCMC CBD, and many others. View more  More jobs from this employer</attribute>
    </and>
  </instance>
