<?xml version='1.0' encoding="UTF-8"?>
<?xml-stylesheet href="..\.style\data.xsl" type="text/xsl"?>
  <instance source="file:/D:/workspaces/ofwi/RoadRunnerOriginal/output/vnwork/html/VNW_mprmarketing493358jd.html" name="VNW_mprmarketing493358jd">
    <and>
      <attribute label="_A_">Nam PR Marketing job - VietnamWorks</attribute>
      <attribute label="_B_">Nam PR Marketing</attribute>
      <attribute label="_C_">Nam PR Marketing</attribute>
      <attribute label="_D_">Công Ty Cổ Phần Karofi</attribute>
      <attribute label="_E_">Tòa Nhà Ngôi Sao, Nguyễn Cảnh Dị, Lô 15B, Khu ĐT Đại Kim, Hoàng Mai, Hà Nội</attribute>
      <attribute label="_F_">1. Xây dựng quan hệ với báo chí, truyền thông, các đối tác có liên quan 2. Là đầu mối của công ty trong việc đưa ra các thông điệp với bên ngoài qua báo chí/truyền thông 3. Tổng hợp và báo cáo các thông tin về công ty được đưa trên báo chí/truyền thông 4. Duy trì các mối quan hệ với khách hàng hiện có. Phát triển thị trường, khách hàng mới. 5. Nghiên cứu, dự báo các chiều hướng dư luận có khả năng ảnh hưởng đến cty 6. Tư vấn và thực hiện các biện pháp khắc phục khi có thông tin xấu trên thị trường 8. Tổ chức các sự kiện 9. Quản lý hệ thống thông tin marketing 10. Xây dựng và quản lý trang web của công ty: Phụ trách viết bài PR, thông cáo báo chí, phát triển nội dung website.. 11. Hỗ trợ trưởng phòng Marketing đánh giá các hoạt động truyền thông như: quản trị các bài đăng truyền thông và nội dung website, đánh giá mức phủ sóng của tưng dự án truyền thông. 12. Xây dựng và quản lý các hình thức PR nội bộ công ty</attribute>
      <attribute label="_G_">1. Trình độ học vấn/chuyên môn - Báo chí/Ngoại Thương/Kinh Tế/Ngoại Giao/Ngoại Ngữ - Sử dụng thành thạo tin học văn phòng, Internet.  2. Kỹ năng: 2.1 Lập kế hoạch, tổ chức và điều phối 2.2. Quản lý hiệu suất 2.3. Ra quyết định 2.4. Đàm phám và giải quyết mâu thuẫn 2.5. Chia sẻ tầm nhìn 2.6 Quảng bá hình hành Công ty 2.7. Xây dựng mối quan hệ 2.8. Định hướng khách hàng 2.9. Kỹ năng giao tiếp 2.10. Kỹ năng bán hàng 2.11. Giải quyết khiếu nại  3. Kinh nghiệm: 3.1. Có ít nhất 3 năm kinh nghiệm làm việc ở vị trí tương đương  4. Phẩm chất cá nhân - thái độ - hành vi 4.1. Tự tin 4.2. Gải quyết vấn đề 4.3. Định hướng hành động 4.4. Dám nghĩ dám làm 4.5 Đam mê thành công  5. Ứng viên biết lái xe ô tô  ** Điều kiện làm việc 1. Thời gian làm việc: Từ thứ 2 đến thứ 7 2. Địa điểm làm việc: Văn phòng Công ty 3. Phương tiện làm việc: - Cung cấp bàn ghế làm việc, tủ hồ sơ - Máy vi tính, điện thoại  ** Quyền hạn: Được quyền tham gia góp ý kiến và đề xuất giải pháp để giải quyết các vấn đề liên quan lĩnh vực Marketing truyền thông của Công ty.</attribute>
      <attribute label="_H_">Negotiable</attribute>
      <attribute label="_I_">Experienced (Non-Manager)</attribute>
      <attribute label="_J_">Advertising/Promotion/PRMarketingSales</attribute>
      <attribute label="_K_">Ha Noi</attribute>
      <attribute label="_L_">Any</attribute>
      <attribute label="_M_">1597 Views</attribute>
      <attribute label="_N_">05 Aug Expires</attribute>
      <subtree>
<DIV class="row"> 
        <DIV class="col-md-3 col-sm-3 box-md "> 
         <DIV class="logo-cus"> 
          <IMG alt="Employer's logo - Công Ty Cổ Phần Karofi" src="http://images.vietnamworks.com/pictureofcompany/f3/10103729.jpg"/> 
         </DIV> 
        </DIV> 
        <DIV class="col-md-9 col-sm-9"> 
         <H3> Công Ty Cổ Phần Karofi <SMALL>Tòa Nhà Ngôi Sao, Nguyễn Cảnh Dị, Lô 15B, Khu ĐT Đại Kim, Hoàng Mai, Hà Nội</SMALL> </H3> 
        </DIV> 
        <DIV class="col-md-9 col-sm-9">  Contact person: 
         <STRONG>Ms.Diep</STRONG> Company size: 
         <STRONG>N/a</STRONG>  
        </DIV> 
       </DIV>      </subtree>
      <attribute label="_O_">Tập đoàn KAROFI mang trong mình sứ mệnh cung cấp giải pháp tối ưu nhất cho nguồn nước sinh hoạt trở nên tinh khiết đến mọi gia đình. Với sự mệnh đó, hơn 10 năm qua tập đoàn KAROFI đã phát triển vai trò là một nhà nhập khẩu, lắp ráp lớn trên thị trường Việt Nam, cung cấp máy lọc nước cho rất nhiều đơn vị trong ngành trên thị trường máy lọc.  Nhận thấy, các đơn vị tham gia vào thị trường chưa thực sự đáp ứng được những mong muốn của khách hàng về sản phẩm, dịch vụ, thương hiệu….Do đó, nhãn máy lọc nước KAROFI được tung ra thị trường cách đây chưa tròn 2 năm, và đã ghi đậm được dấu ấn trong một thời gian ngắn; với mạng lưới gần 1.500 điểm bán trên toàn quốc; trở thành đối tác đầu tiên và duy nhất tại Việt Nam trong chiến lược đồng phát triển thương hiệu với tập đoàn Dow của Mỹ - một trong 10 tập đoàn đa quốc gia được vinh danh bảo vệ thế giới; thực hiện những bước đầu tiên trong một chiến lược truyền thông lớn, khoa học và mang tính đột phá trong năm 2014 này.  Cuộc nghiên cứu độc lập về thị trường máy lọc nước được thực hiện bởi một đơn vị nghiên cứu thị trường uy tín, chuyên nghiệp, nhiều năm kinh nghiệm vào cuối năm 2013, đã đưa ra kết luận “Karofi là một trong 2 thương hiệu hàng đầu về thiết bị lọc nước tại Việt Nam”  Với mục tiêu, trở thành thương hiệu số 1 về thiết bị lọc nước nói riêng ( 2015), và ngành hàng gia dụng nói chung (2018). Karofi đã chuẩn bị kỹ càng về sức mạnh tài chính cũng như nền móng vững chắc cho mọi hoạt động của doanh nghiệp trên bước đường tiến đến mục tiêu.  Tập đoàn Karofi luôn tìm kiếm và chào đón các ứng viên giỏi, có chung chí hướng tham gia vào đội ngũ của KAROFI để tạo nên một bức tranh, một guồng máy, một hệ thống hoạt động hoàn hảo nhằm cùng nhau tiến đến và chia sẻ những thành công.  Website: http://www.karofi.com.vn Quy mô công ty: N/a Tên người liên hệ: Ms Diep View more  More jobs from this employer</attribute>
    </and>
  </instance>
