<?xml version='1.0' encoding="UTF-8"?>
<?xml-stylesheet href="..\.style\data.xsl" type="text/xsl"?>
  <instance source="file:/D:/workspaces/ofwi/RoadRunnerOriginal/output/vnwork/html/VNW_groupleader3494862jd.html" name="VNW_groupleader3494862jd">
    <and>
      <attribute label="_A_">Production Group Leader job - VietnamWorks</attribute>
      <attribute label="_B_">Production Group Leader</attribute>
      <attribute label="_C_">Production Group Leader</attribute>
      <attribute label="_D_">Nokia (Vietnam) Limited Liability Company</attribute>
      <attribute label="_E_">No. 8 Street 6, VSIP Bac Ninh Service, Urban and Industrial Park, Phu Chan Commune, Tu Son Town, Bac Ninh Province</attribute>
      <attribute label="_F_">- End to end ownership from assigned group: - Group resources planning and arrangement against fine scheduling;  - Production delivery – OTD, production efficiency - Safety – Zero Harm Culture – Incident rate; - Quality – DQ, MFR, Audit failures; Kaizen;  - Cost – Scrap rate, MFR; - Ensure DL technical competence are up to required level; - Grievance redress as per policy, promote &amp; adhere to Nokia Values</attribute>
      <attribute label="_G_">- Production experience 5-7 years, handling 500+directs  - Quality problem solving tools &amp; methods  - Exposure to Cost Governance  - Supervisory skills  - Interpersonal relationship skill - E2E Manufacturing process understanding - Planning and logistics knowledge - Managerial courage - WORK IN SHIFTS</attribute>
      <attribute label="_H_">Team Leader/Supervisor</attribute>
      <attribute label="_I_">Electrical/ElectronicsHigh TechnologyProduction/Process</attribute>
      <attribute label="_J_">Bac Ninh</attribute>
      <attribute label="_K_">English</attribute>
      <attribute label="_L_">64 Views</attribute>
      <attribute label="_M_">27 Aug Expires</attribute>
      <subtree>
<DIV class="row"> 
        <DIV class="col-md-3 col-sm-3 box-md "> 
         <DIV class="logo-cus"> 
          <IMG alt="Employer's logo - Nokia (Vietnam) Limited Liability Company" src="http://images.vietnamworks.com/pictureofcompany/86/8926432.png"/> 
         </DIV> 
        </DIV> 
        <DIV class="col-md-9 col-sm-9"> 
         <H3> Nokia (Vietnam) Limited Liability Company <SMALL>No. 8 Street 6, VSIP Bac Ninh Service, Urban and Industrial Park, Phu Chan Commune, Tu Son Town, Bac Ninh Province</SMALL> </H3> 
        </DIV> 
        <DIV class="col-md-9 col-sm-9">  Contact person: 
         <STRONG>Bui Mai Uyen</STRONG> Company size: 
         <STRONG>5,000-9,999</STRONG>  
        </DIV> 
       </DIV>      </subtree>
      <attribute label="_N_">Everyday, 1/5 world population use Nokia mobile phones. Nokia – one of global leaders in mobile communications whose products have become an integral part of the lives of people around the world. Sharing experiences, accessing information, finding your way or simply speaking to one another, Nokia is there to help you.   Connecting people is our mission. Our goal is to build great mobile products that enable billions of people worldwide to enjoy more of what life has to offer.  Nokia Vietnam is proud to be the newest and the most special Nokia manufacturer globally. We go on an adventure every day. Join us to build and help create an exciting new chapter in the mobile industry. Apply your skills and creativity to explore the possibilities of a rapidly changing world. We care about each and every one of our team member, not only about your career, but your life as a whole.  We are looking for the following positions and hope receiving your application and CVs. Join us to build a career you’ll be proud of! View more  More jobs from this employer</attribute>
    </and>
  </instance>
