<?xml version='1.0' encoding="UTF-8"?>
<?xml-stylesheet href="..\.style\data.xsl" type="text/xsl"?>
  <instance source="file:/D:/workspaces/ofwi/RoadRunnerOriginal/output/vnwork/html/VNW_archanalyst2494871jd.html" name="VNW_archanalyst2494871jd">
    <and>
      <attribute label="_A_">Research Analyst job - VietnamWorks</attribute>
      <attribute label="_B_">Research Analyst</attribute>
      <attribute label="_C_">Research Analyst</attribute>
      <attribute label="_D_">Home Credit Group</attribute>
      <attribute label="_E_">194 Golden Buidling, 473 Dien Bien Phu, Ward 25, Binh Thanh District, HCMC</attribute>
      <attribute label="_F_">Build the information package in connection with real internal sales result and competitor’s sales result and partner’s sales result (news in media channel/information collected from network: product/sales activities/expansion/new channel…)  Survey design for internal development projects  In charge of in house researches such as mystery shoppers, dealer satisfaction, including field work, data processing, charting, presentation, follow up.  Analyze data in house to specify customers profile, segmentation  Track and report about financial market, banking and competitors  Understand the needs of company to recommend buying data within allocated budget</attribute>
      <attribute label="_G_">University graduate major in Business Administration, Foreign Trade, Economics Experience in sale field At least 3 years of experience in research. Strong in quantitative research is an advantage Fluent English  Good command of computer skills: Word, Excel, Power point, SPSS, Eviews Proven business management competency Analytic skill, presentation skill High sense of confidentiality</attribute>
      <attribute label="_H_">Experienced (Non-Manager)</attribute>
      <attribute label="_I_">Finance/Investment</attribute>
      <attribute label="_J_">Ho Chi Minh</attribute>
      <attribute label="_K_">English</attribute>
      <attribute label="_L_">162 Views</attribute>
      <attribute label="_M_">27 Aug Expires</attribute>
      <subtree>
<DIV class="row"> 
        <DIV class="col-md-3 col-sm-3 box-md "> 
         <DIV class="logo-cus"> 
          <IMG alt="Employer's logo - Home Credit Group" src="http://images.vietnamworks.com/pictureofcompany/cc/8511266.png"/> 
         </DIV> 
        </DIV> 
        <DIV class="col-md-9 col-sm-9"> 
         <H3> Home Credit Group <SMALL>194 Golden Buidling, 473 Dien Bien Phu, Ward 25, Binh Thanh District, HCMC</SMALL> </H3> 
        </DIV> 
        <DIV class="col-md-9 col-sm-9">  Contact person: 
         <STRONG>HR Department</STRONG> Company size: 
         <STRONG>5,000-9,999</STRONG>  
        </DIV> 
       </DIV>      </subtree>
      <attribute label="_N_">Overview of Home Credit Group  Home Credit is found and invested by PPF; one of the largest investment and finance groups in CEE invests to multi-business range from banking, insurance to real estate, energy, metal mining, agriculture and retail.  Founded in 1997, Home Credit Group is focused on the nine key consumer finance markets of the Czech Republic, Slovakia, the Russian Federation, Belarus, Kazakhstan, China, Vietnam, India, Indonesia and is developing a new business in Philippines. Its 44,800 employees have so far served more than 35 million customers at over 125,006 distribution points across all geographies where the services are provided under the Home Credit brand.  Home Credit in Vietnam  In April 2009, PPF Vietnam Finance Company Ltd was successful in obtaining a license to establish a 100% foreign-owned non-banking financial.   With its quick, simple, convenient services, Home Credit brings the best financial solutions to customers. We are now providing high demand services of: • Motorbike installment loans • Consumer loans • Cash loans  Currently we are covering 63 cities and provinces with more than 5,000 points of sales nationwide. View more  More jobs from this employer</attribute>
    </and>
  </instance>
